{
  "name": "Barcelona ARR & DEP (LEBL)",
  "id": "d0ea477e-35ed-409c-861f-99001a19d94a",
  "composites": [
    {
      "id": "0f591c2c-fe1f-4982-8679-9afc15be429c",
      "identifier": "LEBL",
      "atisType": "Arrival",
      "codeRange": {
        "low": "A",
        "high": "Z"
      },
      "frequency": 118650000,
      "atisVoice": {
        "useTextToSpeech": true,
        "voice": "Default"
      },
      "idsEndpoint": "",
      "useNotamPrefix": false,
      "useDecimalTerminology": true,
      "airportConditionsBeforeFreeText": false,
      "notamsBeforeFreeText": false,
      "presets": [
        {
          "id": "87484a4c-2f5a-4166-8b35-3b74ec5cca86",
          "name": "WRL",
          "airportConditions": "RWY IN USE FOR ARRIVALS 24 RIGHT. EXPECT ILS Z APPROACH RWY 24 RIGHT.",
          "notams": "CAUTION, R-NAV APPROACH TRANSITIONS IN USE FROM INITIAL APPROACH FIX. CHECK FMS, EXPECT 2W APPROACH TRANSITIONS FOR RUNWAY 24 RIGHT. HIGH INTENSITY RUNWAY OPERATIONS IN FORCE.",
          "template": "THIS IS [FACILITY] ATIS INFORMATION [ATIS_CODE]. AT TIME [OBS_TIME]. [ARPT_COND]. [NOTAMS]. [FULL_WX_STRING]. [TL]. THIS WAS [FACILITY] ATIS INFORMATION [ATIS_CODE].",
          "externalGenerator": {
            "enabled": false
          }
        },
        {
          "id": "988b2a98-c4c3-4ad8-9a7b-4aa747843e5a",
          "name": "WLL",
          "airportConditions": "RWY IN USE FOR ARRIVALS 24 LEFT. EXPECT ILS Z APPROACH RWY 24 LEFT.",
          "notams": "CAUTION, R-NAV APPROACH TRANSITIONS IN USE FROM INITIAL APPROACH FIX. CHECK FMS, EXPECT 2L APPROACH TRANSITIONS FOR RUNWAY 24 LEFT. HIGH INTENSITY RUNWAY OPERATIONS IN FORCE.",
          "template": "THIS IS [FACILITY] ATIS INFORMATION [ATIS_CODE]. AT TIME [OBS_TIME]. [ARPT_COND]. [NOTAMS]. [FULL_WX_STRING]. [TL]. THIS WAS [FACILITY] ATIS INFORMATION [ATIS_CODE].",
          "externalGenerator": {
            "enabled": false
          }
        },
        {
          "id": "fe9fb46b-8007-409d-90d5-cbdf5dc67930",
          "name": "ENR",
          "airportConditions": "RWY IN USE FOR ARRIVALS 02. EXPECT ILS Z APPROACH RWY 02.",
          "notams": "CAUTION, R-NAV APPROACH TRANSITIONS IN USE FROM INITIAL APPROACH FIX. CHECK FMS, EXPECT 2N APPROACH TRANSITIONS FOR RUNWAY 02.",
          "template": "THIS IS [FACILITY] ATIS INFORMATION [ATIS_CODE]. AT TIME [OBS_TIME]. [ARPT_COND]. [NOTAMS]. [FULL_WX_STRING]. [TL]. THIS WAS [FACILITY] ATIS INFORMATION [ATIS_CODE].",
          "externalGenerator": {
            "enabled": false
          }
        },
        {
          "id": "ee2cb5d0-1dd1-4735-8ce3-715c7024b50d",
          "name": "ELR",
          "airportConditions": "RWY IN USE FOR ARRIVALS 06 LEFT. EXPECT ILS Z APPROACH RWY 06 LEFT.",
          "notams": "CAUTION, R-NAV APPROACH TRANSITIONS IN USE FROM INITIAL APPROACH FIX. CHECK FMS, EXPECT 2E APPROACH TRANSITIONS FOR RUNWAY 06 LEFT. HIGH INTENSITY RUNWAY OPERATIONS IN FORCE.",
          "template": "THIS IS [FACILITY] ATIS INFORMATION [ATIS_CODE]. AT TIME [OBS_TIME]. [ARPT_COND]. [NOTAMS]. [FULL_WX_STRING]. [TL]. THIS WAS [FACILITY] ATIS INFORMATION [ATIS_CODE].",
          "externalGenerator": {
            "enabled": false
          }
        }
      ],
      "contractions": [
        {
          "string": "W",
          "spoken": "WHISKEY"
        },
        {
          "string": "E",
          "spoken": "ECHO"
        },
        {
          "string": "N",
          "spoken": "NOVEMBER"
        },
        {
          "string": "L",
          "spoken": "LIMA"
        },
        {
          "string": "R-NAV",
          "spoken": "ARE-NAV"
        },
        {
          "string": "Z",
          "spoken": "ZULU"
        },
        {
          "string": "UTC",
          "spoken": "YOU-T-SEE"
        },
        {
          "string": "Y",
          "spoken": "YANKEE"
        },
        {
          "string": "RWY",
          "spoken": "RUNWAY"
        },
        {
          "string": "RWYS",
          "spoken": "RUNWAYS"
        },
        {
          "string": "NOSIG",
          "spoken": "NO-SIG"
        },
        {
          "string": "2W",
          "spoken": "TWO WHISKEY"
        },
        {
          "string": "2L",
          "spoken": "TWO LIMA"
        },
        {
          "string": "2N",
          "spoken": "TWO NOVEMBER"
        },
        {
          "string": "2E",
          "spoken": "TWO ECHO"
        }
      ],
      "airportConditionDefinitions": [],
      "notamDefinitions": [],
      "atisFormat": {
        "observationTime": {
          "template": {
            "text": "{time}Z",
            "voice": "{time} ZULU {special}"
          }
        },
        "surfaceWind": {
          "speakLeadingZero": false,
          "magneticVariation": {
            "enabled": false,
            "magneticDegrees": 0
          },
          "standard": {
            "template": {
              "text": "{wind_dir}{wind_spd}KT",
              "voice": "WIND {wind_dir} AT {wind_spd}"
            }
          },
          "standardGust": {
            "template": {
              "text": "{wind_dir}{wind_spd}G{wind_gust}KT",
              "voice": "WIND {wind_dir} AT {wind_spd} GUSTS {wind_gust}"
            }
          },
          "variable": {
            "template": {
              "text": "VRB{wind_spd}KT",
              "voice": "WIND VARIABLE AT {wind_spd}"
            }
          },
          "variableGust": {
            "template": {
              "text": "VRB{wind_spd}G{wind_gust}KT",
              "voice": "WIND VARIABLE AT {wind_spd} GUSTS {wind_gust}"
            }
          },
          "variableDirection": {
            "template": {
              "text": "{wind_vmin}V{wind_vmax}",
              "voice": "WIND VARIABLE BETWEEN {wind_vmin} AND {wind_vmax}"
            }
          },
          "calm": {
            "calmWindSpeed": 2,
            "template": {
              "text": "{wind}",
              "voice": "WIND CALM"
            }
          }
        },
        "visibility": {
          "north": "to the north",
          "northEast": "to the north-east",
          "east": "to the east",
          "southEast": "to the south-east",
          "south": "to the south",
          "southWest": "to the south-west",
          "west": "to the west",
          "northWest": "to the north-west",
          "unlimitedVisibilityVoice": "visibility 10 kilometers or more",
          "unlimitedVisibilityText": "VIS 10KM",
          "includeVisibilitySuffix": true,
          "metersCutoff": 5000,
          "template": {
            "text": "{visibility}",
            "voice": "VISIBILITY {visibility}"
          }
        },
        "presentWeather": {
          "lightIntensity": "light",
          "moderateIntensity": "",
          "heavyIntensity": "heavy",
          "vicinity": "in vicinity",
          "weatherTypes": {
            "DZ": "drizzle",
            "RA": "rain",
            "SN": "snow",
            "SG": "snow grains",
            "IC": "ice crystals",
            "PL": "ice pellets",
            "GR": "hail",
            "GS": "small hail",
            "UP": "unknown precipitation",
            "BR": "mist",
            "FG": "fog",
            "FU": "smoke",
            "VA": "volcanic ash",
            "DU": "widespread dust",
            "SA": "sand",
            "HZ": "haze",
            "PY": "spray",
            "PO": "well developed dust, sand whirls",
            "SQ": "squalls",
            "FC": "funnel cloud tornado waterspout",
            "SS": "sandstorm",
            "DS": "dust storm"
          },
          "weatherDescriptors": {
            "PR": "partial",
            "BC": "patches",
            "MI": "shallow",
            "DR": "low drifting",
            "BL": "blowing",
            "SH": "showers",
            "TS": "thunderstorm",
            "FZ": "freezing"
          },
          "template": {
            "text": "{weather}",
            "voice": "{weather}"
          }
        },
        "clouds": {
          "identifyCeilingLayer": true,
          "convertToMetric": false,
          "undeterminedLayerAltitude": {
            "text": "undetermined",
            "voice": "undetermined"
          },
          "types": {
            "FEW": {
              "$type": "Vatsim.Vatis.Profiles.AtisFormat.Nodes.CloudType, vATIS",
              "text": "FEW{altitude}",
              "voice": "few clouds at {altitude}"
            },
            "SCT": {
              "$type": "Vatsim.Vatis.Profiles.AtisFormat.Nodes.CloudType, vATIS",
              "text": "SCT{altitude}{convective}",
              "voice": "{altitude} scattered {convective}"
            },
            "BKN": {
              "$type": "Vatsim.Vatis.Profiles.AtisFormat.Nodes.CloudType, vATIS",
              "text": "BKN{altitude}{convective}",
              "voice": "{altitude} broken {convective}"
            },
            "OVC": {
              "$type": "Vatsim.Vatis.Profiles.AtisFormat.Nodes.CloudType, vATIS",
              "text": "OVC{altitude}{convective}",
              "voice": "{altitude} overcast {convective}"
            },
            "VV": {
              "$type": "Vatsim.Vatis.Profiles.AtisFormat.Nodes.CloudType, vATIS",
              "text": "VV{altitude}",
              "voice": "indefinite ceiling {altitude}"
            },
            "NSC": {
              "$type": "Vatsim.Vatis.Profiles.AtisFormat.Nodes.CloudType, vATIS",
              "text": "NSC",
              "voice": "no significant clouds"
            },
            "NCD": {
              "$type": "Vatsim.Vatis.Profiles.AtisFormat.Nodes.CloudType, vATIS",
              "text": "NCD",
              "voice": "no clouds detected"
            },
            "CLR": {
              "$type": "Vatsim.Vatis.Profiles.AtisFormat.Nodes.CloudType, vATIS",
              "text": "CLR",
              "voice": "sky clear below one-two thousand"
            },
            "SKC": {
              "$type": "Vatsim.Vatis.Profiles.AtisFormat.Nodes.CloudType, vATIS",
              "text": "SKC",
              "voice": "sky clear"
            }
          },
          "convectiveTypes": {
            "CB": "cumulonimbus",
            "TCU": "towering cumulus"
          },
          "template": {
            "text": "{clouds}",
            "voice": "{clouds}"
          }
        },
        "temperature": {
          "usePlusPrefix": false,
          "pronounceLeadingZero": false,
          "template": {
            "text": "{temp}",
            "voice": "TEMPERATURE {temp}"
          }
        },
        "dewpoint": {
          "usePlusPrefix": false,
          "pronounceLeadingZero": false,
          "template": {
            "text": "{dewpoint}",
            "voice": "DEWPOINT {dewpoint}"
          }
        },
        "altimeter": {
          "pronounceDecimal": false,
          "template": {
            "text": "Q{altimeter}",
            "voice": "QNH {altimeter}"
          }
        },
        "transitionLevel": {
          "values": [
            {
              "low": 1032,
              "high": 1050,
              "altitude": 65
            },
            {
              "low": 1014,
              "high": 1031,
              "altitude": 70
            },
            {
              "low": 996,
              "high": 1013,
              "altitude": 75
            },
            {
              "low": 978,
              "high": 995,
              "altitude": 80
            },
            {
              "low": 960,
              "high": 977,
              "altitude": 85
            },
            {
              "low": 942,
              "high": 959,
              "altitude": 90
            }
          ],
          "template": {
            "text": "TRANSITION LEVEL {trl}",
            "voice": "TRANSITION LEVEL {trl}"
          }
        },
        "closingStatement": {
          "autoIncludeClosingStatement": true,
          "template": {
            "text": "...ADVS YOU HAVE INFO {letter}",
            "voice": "ADVISE ON INITIAL CONTACT, YOU HAVE INFORMATION {letter|word}"
          }
        }
      }
    },
    {
      "id": "e3fe5697-cb4c-45ba-9e0e-dd99b82190e6",
      "identifier": "LEBL",
      "atisType": "Departure",
      "codeRange": {
        "low": "A",
        "high": "Z"
      },
      "frequency": 121975000,
      "atisVoice": {
        "useTextToSpeech": true,
        "voice": "Default"
      },
      "idsEndpoint": "",
      "useNotamPrefix": false,
      "useDecimalTerminology": true,
      "airportConditionsBeforeFreeText": false,
      "notamsBeforeFreeText": false,
      "presets": [
        {
          "id": "3319d800-dc71-485a-a897-111047c0eb8e",
          "name": "WRL",
          "airportConditions": "RWY IN USE FOR DEPARTURES 24 LEFT.",
          "template": "THIS IS [FACILITY] ATIS INFORMATION [ATIS_CODE]. AT TIME [OBS_TIME]. [ARPT_COND]. [NOTAMS]. [FULL_WX_STRING]. [TL]. THIS WAS [FACILITY] ATIS INFORMATION [ATIS_CODE].",
          "externalGenerator": {
            "enabled": false
          }
        },
        {
          "id": "282f1a03-ff22-4a66-8186-dc6ef906e1f7",
          "name": "WLL",
          "airportConditions": "RWY IN USE FOR DEPARTURES 24 LEFT.",
          "template": "THIS IS [FACILITY] ATIS INFORMATION [ATIS_CODE]. AT TIME [OBS_TIME]. [ARPT_COND]. [NOTAMS]. [FULL_WX_STRING]. [TL]. THIS WAS [FACILITY] ATIS INFORMATION [ATIS_CODE].",
          "externalGenerator": {
            "enabled": false
          }
        },
        {
          "id": "ac5cef74-6844-422f-989c-3840ac14a2b5",
          "name": "ENR",
          "airportConditions": "RWY IN USE FOR DEPARTURES 06 RIGHT.",
          "template": "THIS IS [FACILITY] ATIS INFORMATION [ATIS_CODE]. AT TIME [OBS_TIME]. [ARPT_COND]. [NOTAMS]. [FULL_WX_STRING]. [TL]. THIS WAS [FACILITY] ATIS INFORMATION [ATIS_CODE].",
          "externalGenerator": {
            "enabled": false
          }
        },
        {
          "id": "8feae6af-1a28-47b6-81f9-72cf323f904e",
          "name": "ELR",
          "airportConditions": "RWY IN USE FOR DEPARTURES 06 RIGHT.",
          "template": "THIS IS [FACILITY] ATIS INFORMATION [ATIS_CODE]. AT TIME [OBS_TIME]. [ARPT_COND]. [NOTAMS]. [FULL_WX_STRING]. [TL]. THIS WAS [FACILITY] ATIS INFORMATION [ATIS_CODE].",
          "externalGenerator": {
            "enabled": false
          }
        }
      ],
      "contractions": [
        {
          "string": "W",
          "spoken": "WHISKEY"
        },
        {
          "string": "E",
          "spoken": "ECHO"
        },
        {
          "string": "N",
          "spoken": "NOVEMBER"
        },
        {
          "string": "L",
          "spoken": "LIMA"
        },
        {
          "string": "R-NAV",
          "spoken": "ARE-NAV"
        },
        {
          "string": "Z",
          "spoken": "ZULU"
        },
        {
          "string": "UTC",
          "spoken": "YOU-T-SEE"
        },
        {
          "string": "Y",
          "spoken": "YANKEE"
        },
        {
          "string": "RWY",
          "spoken": "RUNWAY"
        },
        {
          "string": "RWYS",
          "spoken": "RUNWAYS"
        },
        {
          "string": "NOSIG",
          "spoken": "NO-SIG"
        }
      ],
      "airportConditionDefinitions": [],
      "notamDefinitions": [],
      "atisFormat": {
        "observationTime": {
          "template": {
            "text": "{time}Z",
            "voice": "{time} ZULU {special}"
          }
        },
        "surfaceWind": {
          "speakLeadingZero": false,
          "magneticVariation": {
            "enabled": false,
            "magneticDegrees": 0
          },
          "standard": {
            "template": {
              "text": "{wind_dir}{wind_spd}KT",
              "voice": "WIND {wind_dir} AT {wind_spd}"
            }
          },
          "standardGust": {
            "template": {
              "text": "{wind_dir}{wind_spd}G{wind_gust}KT",
              "voice": "WIND {wind_dir} AT {wind_spd} GUSTS {wind_gust}"
            }
          },
          "variable": {
            "template": {
              "text": "VRB{wind_spd}KT",
              "voice": "WIND VARIABLE AT {wind_spd}"
            }
          },
          "variableGust": {
            "template": {
              "text": "VRB{wind_spd}G{wind_gust}KT",
              "voice": "WIND VARIABLE AT {wind_spd} GUSTS {wind_gust}"
            }
          },
          "variableDirection": {
            "template": {
              "text": "{wind_vmin}V{wind_vmax}",
              "voice": "WIND VARIABLE BETWEEN {wind_vmin} AND {wind_vmax}"
            }
          },
          "calm": {
            "calmWindSpeed": 2,
            "template": {
              "text": "{wind}",
              "voice": "WIND CALM"
            }
          }
        },
        "visibility": {
          "north": "to the north",
          "northEast": "to the north-east",
          "east": "to the east",
          "southEast": "to the south-east",
          "south": "to the south",
          "southWest": "to the south-west",
          "west": "to the west",
          "northWest": "to the north-west",
          "unlimitedVisibilityVoice": "visibility 10 kilometers or more",
          "unlimitedVisibilityText": "VIS 10KM",
          "includeVisibilitySuffix": true,
          "metersCutoff": 5000,
          "template": {
            "text": "{visibility}",
            "voice": "VISIBILITY {visibility}"
          }
        },
        "presentWeather": {
          "lightIntensity": "light",
          "moderateIntensity": "",
          "heavyIntensity": "heavy",
          "vicinity": "in vicinity",
          "weatherTypes": {
            "DZ": "drizzle",
            "RA": "rain",
            "SN": "snow",
            "SG": "snow grains",
            "IC": "ice crystals",
            "PL": "ice pellets",
            "GR": "hail",
            "GS": "small hail",
            "UP": "unknown precipitation",
            "BR": "mist",
            "FG": "fog",
            "FU": "smoke",
            "VA": "volcanic ash",
            "DU": "widespread dust",
            "SA": "sand",
            "HZ": "haze",
            "PY": "spray",
            "PO": "well developed dust, sand whirls",
            "SQ": "squalls",
            "FC": "funnel cloud tornado waterspout",
            "SS": "sandstorm",
            "DS": "dust storm"
          },
          "weatherDescriptors": {
            "PR": "partial",
            "BC": "patches",
            "MI": "shallow",
            "DR": "low drifting",
            "BL": "blowing",
            "SH": "showers",
            "TS": "thunderstorm",
            "FZ": "freezing"
          },
          "template": {
            "text": "{weather}",
            "voice": "{weather}"
          }
        },
        "clouds": {
          "identifyCeilingLayer": true,
          "convertToMetric": false,
          "undeterminedLayerAltitude": {
            "text": "undetermined",
            "voice": "undetermined"
          },
          "types": {
            "FEW": {
              "$type": "Vatsim.Vatis.Profiles.AtisFormat.Nodes.CloudType, vATIS",
              "text": "FEW{altitude}",
              "voice": "few clouds at {altitude}"
            },
            "SCT": {
              "$type": "Vatsim.Vatis.Profiles.AtisFormat.Nodes.CloudType, vATIS",
              "text": "SCT{altitude}{convective}",
              "voice": "{altitude} scattered {convective}"
            },
            "BKN": {
              "$type": "Vatsim.Vatis.Profiles.AtisFormat.Nodes.CloudType, vATIS",
              "text": "BKN{altitude}{convective}",
              "voice": "{altitude} broken {convective}"
            },
            "OVC": {
              "$type": "Vatsim.Vatis.Profiles.AtisFormat.Nodes.CloudType, vATIS",
              "text": "OVC{altitude}{convective}",
              "voice": "{altitude} overcast {convective}"
            },
            "VV": {
              "$type": "Vatsim.Vatis.Profiles.AtisFormat.Nodes.CloudType, vATIS",
              "text": "VV{altitude}",
              "voice": "indefinite ceiling {altitude}"
            },
            "NSC": {
              "$type": "Vatsim.Vatis.Profiles.AtisFormat.Nodes.CloudType, vATIS",
              "text": "NSC",
              "voice": "no significant clouds"
            },
            "NCD": {
              "$type": "Vatsim.Vatis.Profiles.AtisFormat.Nodes.CloudType, vATIS",
              "text": "NCD",
              "voice": "no clouds detected"
            },
            "CLR": {
              "$type": "Vatsim.Vatis.Profiles.AtisFormat.Nodes.CloudType, vATIS",
              "text": "CLR",
              "voice": "sky clear below one-two thousand"
            },
            "SKC": {
              "$type": "Vatsim.Vatis.Profiles.AtisFormat.Nodes.CloudType, vATIS",
              "text": "SKC",
              "voice": "sky clear"
            }
          },
          "convectiveTypes": {
            "CB": "cumulonimbus",
            "TCU": "towering cumulus"
          },
          "template": {
            "text": "{clouds}",
            "voice": "{clouds}"
          }
        },
        "temperature": {
          "usePlusPrefix": false,
          "pronounceLeadingZero": false,
          "template": {
            "text": "{temp}",
            "voice": "TEMPERATURE {temp}"
          }
        },
        "dewpoint": {
          "usePlusPrefix": false,
          "pronounceLeadingZero": false,
          "template": {
            "text": "{dewpoint}",
            "voice": "DEWPOINT {dewpoint}"
          }
        },
        "altimeter": {
          "pronounceDecimal": false,
          "template": {
            "text": "A{altimeter} ({altimeter|text})",
            "voice": "ALTIMETER {altimeter}"
          }
        },
        "transitionLevel": {
          "values": [
            {
              "low": 1032,
              "high": 1050,
              "altitude": 65
            },
            {
              "low": 1014,
              "high": 1031,
              "altitude": 70
            },
            {
              "low": 996,
              "high": 1013,
              "altitude": 75
            },
            {
              "low": 978,
              "high": 995,
              "altitude": 80
            },
            {
              "low": 960,
              "high": 977,
              "altitude": 85
            },
            {
              "low": 942,
              "high": 959,
              "altitude": 90
            }
          ],
          "template": {
            "text": "TRANSITION LEVEL {trl}",
            "voice": "TRANSITION LEVEL {trl}"
          }
        },
        "closingStatement": {
          "autoIncludeClosingStatement": true,
          "template": {
            "text": "...ADVS YOU HAVE INFO {letter}",
            "voice": "ADVISE ON INITIAL CONTACT, YOU HAVE INFORMATION {letter|word}"
          }
        }
      }
    }
  ]
}